lexis/__init__.py
lexis/examples/__init__.py
lexis/examples/drawing_games.py
lexis-0.1.2.dist-info/LICENSE
lexis-0.1.2.dist-info/METADATA
lexis-0.1.2.dist-info/WHEEL
lexis-0.1.2.dist-info/top_level.txt
lexis-0.1.2.dist-info/RECORD
