Metadata-Version: 2.1
Name: lexis
Version: 0.1.2
Summary: Wordnet wrapper - Easy access to words and their relationships
Home-page: https://github.com/thorwhalen/lexis
Author: Thor Whalen
License: apache-2.0
Keywords: words,definitions,lexicon,wordnet,NLP,Natural Language Processing,text mining
Platform: any
License-File: LICENSE
Requires-Dist: i2
Requires-Dist: dol
Requires-Dist: nltk
